bridger/__init__.py
bridger-0.0.1.dev0.dist-info/METADATA
bridger-0.0.1.dev0.dist-info/WHEEL
bridger-0.0.1.dev0.dist-info/top_level.txt
bridger-0.0.1.dev0.dist-info/RECORD
