Metadata-Version: 2.1
Name: bridger
Version: 0.0.1.dev0
Summary: bridger
Home-page: https://github.com/hsulab-arc/Bridger
Author: Matt Durrant
Author-email: matthew@arcinstitute.org
License: UNKNOWN
Platform: UNKNOWN
Classifier: Programming Language :: Python :: 3
Classifier: License :: OSI Approved :: MIT License
Classifier: Operating System :: OS Independent
Requires-Python: >=3.8
